{
  "unversionedId": "Fontes/shsugtran",
  "id": "Fontes/shsugtran",
  "title": "SHSUGTRAN.PRW",
  "description": "Alimentador de tabela temporaria PCZ para transferências automatizadas",
  "source": "@site/docs/2-Fontes/shsugtran.md",
  "sourceDirName": "2-Fontes",
  "slug": "/Fontes/shsugtran",
  "permalink": "/docushark/docs/Fontes/shsugtran",
  "draft": false,
  "tags": [],
  "version": "current",
  "frontMatter": {},
  "sidebar": "tutorialSidebar",
  "previous": {
    "title": "SHPRCCOM.PRW",
    "permalink": "/docushark/docs/Fontes/shprccom"
  },
  "next": {
    "title": "SHTRAABA.PRW",
    "permalink": "/docushark/docs/Fontes/shtraaba"
  }
}